bboxvis/__init__.py
bboxvis/gui.py
bboxvis/tools.py
bboxvis/examples/simple_vis.py
bboxvis-0.0.3.dist-info/LICENSE
bboxvis-0.0.3.dist-info/METADATA
bboxvis-0.0.3.dist-info/WHEEL
bboxvis-0.0.3.dist-info/top_level.txt
bboxvis-0.0.3.dist-info/RECORD
