Metadata-Version: 2.1
Name: bboxvis
Version: 0.0.3
Summary: A small example package for point cloud visualization
Author-email: Chengqi Li <lichengqi0805@gmail.com>
License: Copyright (c) 2018 The Python Packaging Authority
Project-URL: Homepage, https://github.com/lichengqi0805/bboxvis
Project-URL: Bug Tracker, https://github.com/lichengqi0805/bboxvis/issues
Classifier: Programming Language :: Python :: 3
Classifier: License :: OSI Approved :: MIT License
Classifier: Operating System :: OS Independent
Requires-Python: >=3.8
License-File: LICENSE
Requires-Dist: matplotlib (>=3.5.1)
Requires-Dist: numba
Requires-Dist: vispy (==0.9.6)
Requires-Dist: pyzmq
Requires-Dist: scipy
Requires-Dist: loguru
